chess2postgres/__init__.py
chess2postgres/chess2postgres.py
chess2postgres-0.0.3.dist-info/LICENSE
chess2postgres-0.0.3.dist-info/METADATA
chess2postgres-0.0.3.dist-info/WHEEL
chess2postgres-0.0.3.dist-info/top_level.txt
chess2postgres-0.0.3.dist-info/RECORD
