Metadata-Version: 2.1
Name: chess2postgres
Version: 0.0.3
Summary: Simple python library to fetch games directly into Postgres database from Lichess.org using it's API or pgn file containing games.
Home-page: https://github.com/lot022/chess2postgres
Author: lot022
License: MIT
Keywords: chess
Classifier: Programming Language :: Python
Classifier: Operating System :: Unix
Classifier: License :: OSI Approved :: MIT License
Classifier: Topic :: Games/Entertainment :: Board Games
Classifier: Topic :: Software Development :: Libraries :: Python Modules
Classifier: Programming Language :: Python :: 3.7
Classifier: Programming Language :: Python :: 3.8
Classifier: Programming Language :: Python :: 3.9
Classifier: Programming Language :: Python :: 3.10
Requires-Python: >=3.7
License-File: LICENSE
Requires-Dist: berserk
Requires-Dist: chessanalytics
